{
  "pc_no": "C02D6R",
  "modelName": "gemma2:2b-instruct-q4_0",
  "responseFileName": "resp-high.txt",
  "runAt": "250605-1607",
  "scores": {
    "accurate": 5,
    "relevant": 5,
    "organization": 5,
    "totalScore": "100.0",
    "weightedScore": "100.0"
  },
  "performanceMetrics": {
    "totalDuration": "71.56",
    "loadDuration": "6.12",
    "promptEvalCount": 2028,
    "promptEvalDuration": "42.88",
    "promptEvalRate": "47.29",
    "evalCount": 269,
    "evalDuration": "22.55",
    "evalRate": "11.93"
  }
}